pymt_nwm/__init__.py
pymt_nwm/bmi.py
pymt_nwm/data/.DS_Store
pymt_nwm/data/Nwm/.DS_Store
pymt_nwm/data/Nwm/api.yaml
pymt_nwm/data/Nwm/config.yaml
pymt_nwm/data/Nwm/info.yaml
pymt_nwm/data/Nwm/parameters.yaml
pymt_nwm/data/Nwm/run.yaml
pymt_nwm-0.1.dist-info/LICENSE
pymt_nwm-0.1.dist-info/METADATA
pymt_nwm-0.1.dist-info/WHEEL
pymt_nwm-0.1.dist-info/entry_points.txt
pymt_nwm-0.1.dist-info/top_level.txt
pymt_nwm-0.1.dist-info/RECORD
