Metadata-Version: 2.1
Name: pymt-nwm
Version: 0.1
Summary: PyMT plugin for pymt_nwm
Home-page: https://github.com/gantian127/pymt_nwm
Author: Tian Gan
Author-email: gantian127@gmail.com
License: UNKNOWN
Keywords: bmi,pymt
Platform: UNKNOWN
Classifier: Development Status :: 4 - Beta
Classifier: Intended Audience :: Science/Research
Classifier: License :: OSI Approved :: MIT License
Classifier: Operating System :: MacOS :: MacOS X
Classifier: Operating System :: POSIX :: Linux
Classifier: Programming Language :: Python :: 3 :: Only
Classifier: Programming Language :: Python :: 3.8
Requires-Dist: numpy
Requires-Dist: nwm
